baklava/__init__.py
baklava/__version.py
baklava/api.py
baklava/commands.py
baklava/distribution.py
baklava/entrypoint.py
baklava/environment.py
baklava/images.py
baklava/pypi.py
baklava/render.py
baklava/resources/__init__.py
baklava/resources/predict/Dockerfile
baklava/resources/predict/main.py
baklava/resources/predict/nginx.conf
baklava/resources/train/Dockerfile
baklava/resources/train/main.py
baklava-0.0.4.dist-info/LICENSE.md
baklava-0.0.4.dist-info/METADATA
baklava-0.0.4.dist-info/WHEEL
baklava-0.0.4.dist-info/entry_points.txt
baklava-0.0.4.dist-info/top_level.txt
baklava-0.0.4.dist-info/RECORD
